viva_parse/__init__.py
viva_parse/dump.py
viva_parse/nemo.py
viva_parse/parse.py
viva_parse-0.0.3.dist-info/METADATA
viva_parse-0.0.3.dist-info/WHEEL
viva_parse-0.0.3.dist-info/licenses/LICENSE
viva_parse-0.0.3.dist-info/RECORD
