Metadata-Version: 2.1
Name: viva_parse
Version: 0.0.3
Summary: A python package to parse and dump conversations in VIVA style.
Author-email: Sven Schultze <schultze.sven@googlemail.com>
License-File: LICENSE
Classifier: License :: OSI Approved :: MIT License
Classifier: Operating System :: OS Independent
Classifier: Programming Language :: Python :: 3
Requires-Python: >=3.7
Provides-Extra: test
Requires-Dist: pytest; extra == 'test'
